<?xml version="1.0" encoding="UTF-8" ?>
<!DOCTYPE mapper PUBLIC "-//mybatis.org//DTD Mapper 3.0//EN" "http://mybatis.org/dtd/mybatis-3-mapper.dtd" >
<mapper namespace="com.runlion.shop.dao.BspHelpsTypesMapper" >
  <resultMap id="BaseResultMap" type="com.runlion.shop.entity.BspHelpsTypes" >
    <!--
      WARNING - @mbggenerated
      This element is automatically generated by MyBatis Generator, do not modify.
      This element was generated on Fri Jun 26 14:56:27 CST 2015.
    -->
    <result column="helpstypeid" property="helpstypeid" jdbcType="INTEGER" />
    <result column="name" property="name" jdbcType="VARCHAR" />
    <result column="displayorder" property="displayorder" jdbcType="INTEGER" />
  </resultMap>
  
  
    <select id="selecthelpstype" resultType="java.util.HashMap">
		select * from bsp_helpstypes order by displayorder 
	</select>
	
	<select id="count" resultType="java.lang.Integer">
		select count(1) cnt from  bsp_helpstypes
	</select>
	
	<delete id="delete" parameterType="java.lang.Integer" >
    <!--
      WARNING - @mbggenerated
      This element is automatically generated by MyBatis Generator, do not modify.
      This element was generated on Fri Jun 26 14:56:27 CST 2015.
    -->
    delete from bsp_helpstypes
    where helpstypeid = #{ID,jdbcType=INTEGER}
  </delete>
  
    <select id="selectbyid" resultType="java.util.HashMap" parameterType="java.lang.Integer">
		select * from bsp_helpstypes where helpstypeid = #{id,jdbcType=INTEGER}
	</select>
	
	
	<update id="update" parameterType="map" >
		update bsp_helpstypes
		set name = #{name}
		,displayorder = #{displayorder}
		where helpstypeid = #{helpstypeid}
	</update>
	<insert id="insert" parameterType="map">
		insert into bsp_helpstypes(name, displayorder)
		values(#{name}, #{displayorder})
	</insert>
</mapper>